tensor_bridge/__init__.py
tensor_bridge/_tensor_bridge.pxd
tensor_bridge/_version.py
tensor_bridge/imports.py
tensor_bridge/native_tensor_bridge.cu
tensor_bridge/native_tensor_bridge.hpp
tensor_bridge/tensor_bridge.cpython-310-x86_64-linux-gnu.so
tensor_bridge/tensor_bridge.pyi
tensor_bridge/tensor_bridge.pyx
tensor_bridge/types.py
tensor_bridge/utils.py
tensor_bridge-0.2.0.dist-info/LICENSE
tensor_bridge-0.2.0.dist-info/METADATA
tensor_bridge-0.2.0.dist-info/WHEEL
tensor_bridge-0.2.0.dist-info/top_level.txt
tensor_bridge-0.2.0.dist-info/RECORD
