Metadata-Version: 2.1
Name: tensor_bridge
Version: 0.2.0
Summary: Transfer tensors between PyTorch, Jax and more
Home-page: https://github.com/takuseno/tensor-bridge
Author: Takuma Seno
Author-email: takuma.seno@gmail.com
License: MIT License
Requires-Python: >=3.8.0
License-File: LICENSE
